{
    "291074": {
        "geoid": "291074",
        "name": "Ras al-Khaimah",
        "lat": 25.78953,
        "lng": 55.9432,
        "country": "AE",
        "state": "05",
        "population": 115949
    },
    "292223": {
        "geoid": "292223",
        "name": "Dubai",
        "lat": 25.0657,
        "lng": 55.17128,
        "country": "AE",
        "state": "03",
        "population": 1137347
    },
    "292672": {
        "geoid": "292672",
        "name": "Sharjah",
        "lat": 25.33737,
        "lng": 55.41206,
        "country": "AE",
        "state": "06",
        "population": 543733
    },
    "292878": {
        "geoid": "292878",
        "name": "Al Fujayrah",
        "lat": 25.11641,
        "lng": 56.34141,
        "country": "AE",
        "state": "04",
        "population": 62415
    },
    "292913": {
        "geoid": "292913",
        "name": "Al Ain",
        "lat": 24.19167,
        "lng": 55.76056,
        "country": "AE",
        "state": "01",
        "population": 408733
    },
    "292932": {
        "geoid": "292932",
        "name": "Ajman",
        "lat": 25.41111,
        "lng": 55.43504,
        "country": "AE",
        "state": "02",
        "population": 226172
    },
    "292968": {
        "geoid": "292968",
        "name": "Abu Dhabi",
        "lat": 24.46667,
        "lng": 54.36667,
        "country": "AE",
        "state": "01",
        "population": 603492
    }
}