{
    "1821306": {
        "geoid": "1821306",
        "name": "Phnom Penh",
        "lat": 11.56245,
        "lng": 104.91601,
        "country": "KH",
        "state": "22",
        "population": 1573544
    },
    "1821935": {
        "geoid": "1821935",
        "name": "Ta Khmau",
        "lat": 11.48333,
        "lng": 104.95,
        "country": "KH",
        "state": "07",
        "population": 52066
    },
    "1821940": {
        "geoid": "1821940",
        "name": "Takeo",
        "lat": 10.99081,
        "lng": 104.78498,
        "country": "KH",
        "state": "19",
        "population": 843931
    },
    "1822214": {
        "geoid": "1822214",
        "name": "Siem Reap",
        "lat": 13.36179,
        "lng": 103.86056,
        "country": "KH",
        "state": "24",
        "population": 139458
    },
    "1822768": {
        "geoid": "1822768",
        "name": "Pursat",
        "lat": 12.53878,
        "lng": 103.9192,
        "country": "KH",
        "state": "12",
        "population": 52476
    },
    "1830194": {
        "geoid": "1830194",
        "name": "Paôy Pêt",
        "lat": 13.65611,
        "lng": 102.5625,
        "country": "KH",
        "state": "25",
        "population": 79000
    },
    "1831142": {
        "geoid": "1831142",
        "name": "Sihanoukville",
        "lat": 10.60932,
        "lng": 103.52958,
        "country": "KH",
        "state": "28",
        "population": 156691
    },
    "1831167": {
        "geoid": "1831167",
        "name": "Kampong Chhnang",
        "lat": 12.25,
        "lng": 104.66667,
        "country": "KH",
        "state": "03",
        "population": 75244
    },
    "1831173": {
        "geoid": "1831173",
        "name": "Kampong Cham",
        "lat": 11.99339,
        "lng": 105.4635,
        "country": "KH",
        "state": "02",
        "population": 61750
    },
    "1831797": {
        "geoid": "1831797",
        "name": "Battambang",
        "lat": 13.10271,
        "lng": 103.19822,
        "country": "KH",
        "state": "29",
        "population": 150444
    }
}