[
    {
        "ids": {
            "fips": "40",
            "geonames": 865730
        },
        "names": {
            "long": "Berat"
        }
    },
    {
        "ids": {
            "fips": "41",
            "geonames": 865731
        },
        "names": {
            "long": "Dibër"
        }
    },
    {
        "ids": {
            "fips": "43",
            "geonames": 865732
        },
        "names": {
            "long": "Elbasan"
        }
    },
    {
        "ids": {
            "fips": "45",
            "geonames": 865733
        },
        "names": {
            "long": "Gjirokastër"
        }
    },
    {
        "ids": {
            "fips": "46",
            "geonames": 865734
        },
        "names": {
            "long": "Korçë"
        }
    },
    {
        "ids": {
            "fips": "47",
            "geonames": 865735
        },
        "names": {
            "long": "Kukës"
        }
    },
    {
        "ids": {
            "fips": "42",
            "geonames": 3344947
        },
        "names": {
            "long": "Durrës"
        }
    },
    {
        "ids": {
            "fips": "44",
            "geonames": 3344948
        },
        "names": {
            "long": "Fier"
        }
    },
    {
        "ids": {
            "fips": "48",
            "geonames": 3344949
        },
        "names": {
            "long": "Lezhë"
        }
    },
    {
        "ids": {
            "fips": "49",
            "geonames": 3344950
        },
        "names": {
            "long": "Shkodër"
        }
    },
    {
        "ids": {
            "fips": "50",
            "geonames": 3344951
        },
        "names": {
            "long": "Tiranë"
        }
    },
    {
        "ids": {
            "fips": "51",
            "geonames": 3344952
        },
        "names": {
            "long": "Vlorë"
        }
    }
]