[
    {
        "ids": {
            "fips": "01",
            "geonames": 6930701
        },
        "names": {
            "long": "Boucle du Mouhoun"
        }
    },
    {
        "ids": {
            "fips": "02",
            "geonames": 6930703
        },
        "names": {
            "long": "Cascades"
        }
    },
    {
        "ids": {
            "fips": "03",
            "geonames": 6930704
        },
        "names": {
            "long": "Centre"
        }
    },
    {
        "ids": {
            "fips": "04",
            "geonames": 6930705
        },
        "names": {
            "long": "Centre-Est"
        }
    },
    {
        "ids": {
            "fips": "05",
            "geonames": 6930706
        },
        "names": {
            "long": "Centre-Nord"
        }
    },
    {
        "ids": {
            "fips": "06",
            "geonames": 6930707
        },
        "names": {
            "long": "Centre-Ouest"
        }
    },
    {
        "ids": {
            "fips": "07",
            "geonames": 6930708
        },
        "names": {
            "long": "Centre-Sud"
        }
    },
    {
        "ids": {
            "fips": "08",
            "geonames": 6930709
        },
        "names": {
            "long": "Est"
        }
    },
    {
        "ids": {
            "fips": "09",
            "geonames": 6930710
        },
        "names": {
            "long": "Hauts-Bassins"
        }
    },
    {
        "ids": {
            "fips": "10",
            "geonames": 6930711
        },
        "names": {
            "long": "Nord"
        }
    },
    {
        "ids": {
            "fips": "11",
            "geonames": 6930712
        },
        "names": {
            "long": "Plateau-Central"
        }
    },
    {
        "ids": {
            "fips": "12",
            "geonames": 6930713
        },
        "names": {
            "long": "Sahel"
        }
    },
    {
        "ids": {
            "fips": "13",
            "geonames": 6930714
        },
        "names": {
            "long": "Sud-Ouest"
        }
    }
]