[
    {
        "ids": {
            "fips": "01",
            "geonames": 3868621
        },
        "names": {
            "long": "Valparaíso"
        }
    },
    {
        "ids": {
            "fips": "15",
            "geonames": 3870116
        },
        "names": {
            "long": "Tarapacá"
        }
    },
    {
        "ids": {
            "fips": "12",
            "geonames": 3873544
        },
        "names": {
            "long": "Santiago Metropolitan"
        }
    },
    {
        "ids": {
            "fips": "11",
            "geonames": 3880306
        },
        "names": {
            "long": "Maule"
        }
    },
    {
        "ids": {
            "fips": "14",
            "geonames": 3881974
        },
        "names": {
            "long": "Los Lagos"
        }
    },
    {
        "ids": {
            "fips": "08",
            "geonames": 3883281
        },
        "names": {
            "long": "O'Higgins"
        }
    },
    {
        "ids": {
            "fips": "07",
            "geonames": 3893623
        },
        "names": {
            "long": "Coquimbo"
        }
    },
    {
        "ids": {
            "fips": "06",
            "geonames": 3898380
        },
        "names": {
            "long": "Biobío"
        }
    },
    {
        "ids": {
            "fips": "05",
            "geonames": 3899191
        },
        "names": {
            "long": "Atacama"
        }
    },
    {
        "ids": {
            "fips": "04",
            "geonames": 3899463
        },
        "names": {
            "long": "Araucanía"
        }
    },
    {
        "ids": {
            "fips": "03",
            "geonames": 3899537
        },
        "names": {
            "long": "Antofagasta"
        }
    },
    {
        "ids": {
            "fips": "02",
            "geonames": 3900333
        },
        "names": {
            "long": "Aisén"
        }
    },
    {
        "ids": {
            "fips": "10",
            "geonames": 4036650
        },
        "names": {
            "long": "Magallanes"
        }
    },
    {
        "ids": {
            "fips": "16",
            "geonames": 6693562
        },
        "names": {
            "long": "Arica y Parinacota"
        }
    },
    {
        "ids": {
            "fips": "17",
            "geonames": 6693563
        },
        "names": {
            "long": "Los Ríos"
        }
    }
]