[
    {
        "ids": {
            "fips": "20",
            "geonames": 3374161
        },
        "long": {
            "default": "Tarrafal"
        }
    },
    {
        "ids": {
            "fips": "11",
            "geonames": 3374198
        },
        "long": {
            "default": "São Vicente"
        }
    },
    {
        "ids": {
            "fips": "15",
            "geonames": 3374226
        },
        "long": {
            "default": "Santa Catarina"
        }
    },
    {
        "ids": {
            "fips": "08",
            "geonames": 3374249
        },
        "long": {
            "default": "Sal"
        }
    },
    {
        "ids": {
            "fips": "07",
            "geonames": 3374274
        },
        "long": {
            "default": "Ribeira Grande"
        }
    },
    {
        "ids": {
            "fips": "14",
            "geonames": 3374332
        },
        "long": {
            "default": "Praia"
        }
    },
    {
        "ids": {
            "fips": "05",
            "geonames": 3374391
        },
        "long": {
            "default": "Paul"
        }
    },
    {
        "ids": {
            "fips": "04",
            "geonames": 3374487
        },
        "long": {
            "default": "Maio"
        }
    },
    {
        "ids": {
            "fips": "02",
            "geonames": 3374832
        },
        "long": {
            "default": "Brava"
        }
    },
    {
        "ids": {
            "fips": "01",
            "geonames": 3374855
        },
        "long": {
            "default": "Boa Vista"
        }
    },
    {
        "ids": {
            "fips": "13",
            "geonames": 3411924
        },
        "long": {
            "default": "Mosteiros"
        }
    },
    {
        "ids": {
            "fips": "16",
            "geonames": 3411925
        },
        "long": {
            "default": "Santa Cruz"
        }
    },
    {
        "ids": {
            "fips": "17",
            "geonames": 3411926
        },
        "long": {
            "default": "São Domingos"
        }
    },
    {
        "ids": {
            "fips": "18",
            "geonames": 3411927
        },
        "long": {
            "default": "São Filipe"
        }
    },
    {
        "ids": {
            "fips": "19",
            "geonames": 3411928
        },
        "long": {
            "default": "São Miguel"
        }
    },
    {
        "ids": {
            "fips": "21",
            "geonames": 7602868
        },
        "long": {
            "default": "Porto Novo"
        }
    },
    {
        "ids": {
            "fips": "22",
            "geonames": 7602869
        },
        "long": {
            "default": "Ribeira Brava"
        }
    },
    {
        "ids": {
            "fips": "24",
            "geonames": 7602870
        },
        "long": {
            "default": "Santa Catarina do Fogo"
        }
    },
    {
        "ids": {
            "fips": "26",
            "geonames": 7602871
        },
        "long": {
            "default": "São Salvador do Mundo"
        }
    },
    {
        "ids": {
            "fips": "27",
            "geonames": 7602872
        },
        "long": {
            "default": "Tarrafal de São Nicolau"
        }
    },
    {
        "ids": {
            "fips": "25",
            "geonames": 7602873
        },
        "long": {
            "default": "São Lourenço dos Órgãos"
        }
    },
    {
        "ids": {
            "fips": "23",
            "geonames": 7603281
        },
        "long": {
            "default": "Ribeira Grande de Santiago"
        }
    }
]