[
    {
        "ids": {
            "fips": "24",
            "geonames": 347794
        },
        "names": {
            "long": "Sohag"
        }
    },
    {
        "ids": {
            "fips": "27",
            "geonames": 349401
        },
        "names": {
            "long": "North Sinai"
        }
    },
    {
        "ids": {
            "fips": "23",
            "geonames": 350546
        },
        "names": {
            "long": "Qena"
        }
    },
    {
        "ids": {
            "fips": "22",
            "geonames": 352603
        },
        "names": {
            "long": "Matruh"
        }
    },
    {
        "ids": {
            "fips": "21",
            "geonames": 354500
        },
        "names": {
            "long": "Kafr el-Sheikh"
        }
    },
    {
        "ids": {
            "fips": "26",
            "geonames": 355182
        },
        "names": {
            "long": "South Sinai"
        }
    },
    {
        "ids": {
            "fips": "20",
            "geonames": 358044
        },
        "names": {
            "long": "Damietta"
        }
    },
    {
        "ids": {
            "fips": "19",
            "geonames": 358617
        },
        "names": {
            "long": "Port Said"
        }
    },
    {
        "ids": {
            "fips": "18",
            "geonames": 359171
        },
        "names": {
            "long": "Beni Suweif"
        }
    },
    {
        "ids": {
            "fips": "17",
            "geonames": 359781
        },
        "names": {
            "long": "Asyut"
        }
    },
    {
        "ids": {
            "fips": "16",
            "geonames": 359787
        },
        "names": {
            "long": "Aswan"
        }
    },
    {
        "ids": {
            "fips": "15",
            "geonames": 359797
        },
        "names": {
            "long": "Suez"
        }
    },
    {
        "ids": {
            "fips": "14",
            "geonames": 360016
        },
        "names": {
            "long": "Sharqia"
        }
    },
    {
        "ids": {
            "fips": "13",
            "geonames": 360483
        },
        "names": {
            "long": "New Valley"
        }
    },
    {
        "ids": {
            "fips": "12",
            "geonames": 360621
        },
        "names": {
            "long": "Qalyubia"
        }
    },
    {
        "ids": {
            "fips": "11",
            "geonames": 360631
        },
        "names": {
            "long": "Cairo"
        }
    },
    {
        "ids": {
            "fips": "10",
            "geonames": 360688
        },
        "names": {
            "long": "Minya"
        }
    },
    {
        "ids": {
            "fips": "09",
            "geonames": 360689
        },
        "names": {
            "long": "Monufia"
        }
    },
    {
        "ids": {
            "fips": "08",
            "geonames": 360997
        },
        "names": {
            "long": "Giza"
        }
    },
    {
        "ids": {
            "fips": "07",
            "geonames": 361056
        },
        "names": {
            "long": "Ismailia"
        }
    },
    {
        "ids": {
            "fips": "06",
            "geonames": 361059
        },
        "names": {
            "long": "Alexandria"
        }
    },
    {
        "ids": {
            "fips": "05",
            "geonames": 361294
        },
        "names": {
            "long": "Gharbia"
        }
    },
    {
        "ids": {
            "fips": "04",
            "geonames": 361323
        },
        "names": {
            "long": "Faiyum"
        }
    },
    {
        "ids": {
            "fips": "03",
            "geonames": 361370
        },
        "names": {
            "long": "Beheira"
        }
    },
    {
        "ids": {
            "fips": "02",
            "geonames": 361468
        },
        "names": {
            "long": "Red Sea"
        }
    },
    {
        "ids": {
            "fips": "01",
            "geonames": 361849
        },
        "names": {
            "long": "Dakahlia"
        }
    },
    {
        "ids": {
            "fips": "28",
            "geonames": 7603259
        },
        "names": {
            "long": "Luxor"
        }
    }
]