[
    {
        "ids": {
            "fips": "06",
            "geonames": 3579907
        },
        "long": {
            "default": "Saint Patrick"
        }
    },
    {
        "ids": {
            "fips": "05",
            "geonames": 3579913
        },
        "long": {
            "default": "Saint Mark"
        }
    },
    {
        "ids": {
            "fips": "04",
            "geonames": 3579919
        },
        "long": {
            "default": "Saint John"
        }
    },
    {
        "ids": {
            "fips": "03",
            "geonames": 3579926
        },
        "long": {
            "default": "Saint George"
        }
    },
    {
        "ids": {
            "fips": "02",
            "geonames": 3579932
        },
        "long": {
            "default": "Saint David"
        }
    },
    {
        "ids": {
            "fips": "01",
            "geonames": 3579938
        },
        "long": {
            "default": "Saint Andrew"
        }
    },
    {
        "ids": {
            "fips": "10",
            "geonames": 7303836
        },
        "long": {
            "default": "Carriacou and Petite Martinique"
        }
    }
]