[
    {
        "parent": "KN",
        "ids": {
            "fips": "15",
            "geonames": 3575114
        },
        "long": {
            "default": "Trinity Palmetto Point"
        }
    },
    {
        "parent": "KN",
        "ids": {
            "fips": "13",
            "geonames": 3575164
        },
        "long": {
            "default": "Saint Thomas Middle Island"
        }
    },
    {
        "parent": "KN",
        "ids": {
            "fips": "12",
            "geonames": 3575165
        },
        "long": {
            "default": "Saint Thomas Lowland"
        }
    },
    {
        "parent": "KN",
        "ids": {
            "fips": "11",
            "geonames": 3575168
        },
        "long": {
            "default": "Saint Peter Basseterre"
        }
    },
    {
        "parent": "KN",
        "ids": {
            "fips": "10",
            "geonames": 3575171
        },
        "long": {
            "default": "Saint Paul Charlestown"
        }
    },
    {
        "parent": "KN",
        "ids": {
            "fips": "09",
            "geonames": 3575172
        },
        "long": {
            "default": "Saint Paul Capesterre"
        }
    },
    {
        "parent": "KN",
        "ids": {
            "fips": "08",
            "geonames": 3575173
        },
        "long": {
            "default": "Saint Mary Cayon"
        }
    },
    {
        "parent": "KN",
        "ids": {
            "fips": "07",
            "geonames": 3575175
        },
        "long": {
            "default": "Saint John Figtree"
        }
    },
    {
        "parent": "KN",
        "ids": {
            "fips": "06",
            "geonames": 3575176
        },
        "long": {
            "default": "Saint John Capesterre"
        }
    },
    {
        "parent": "KN",
        "ids": {
            "fips": "05",
            "geonames": 3575177
        },
        "long": {
            "default": "Saint James Windwa"
        }
    },
    {
        "parent": "KN",
        "ids": {
            "fips": "04",
            "geonames": 3575179
        },
        "long": {
            "default": "Saint George Gingerland"
        }
    },
    {
        "parent": "KN",
        "ids": {
            "fips": "03",
            "geonames": 3575180
        },
        "long": {
            "default": "Saint George Basseterre"
        }
    },
    {
        "parent": "KN",
        "ids": {
            "fips": "02",
            "geonames": 3575183
        },
        "long": {
            "default": "Saint Anne Sandy Point"
        }
    },
    {
        "parent": "KN",
        "ids": {
            "fips": "01",
            "geonames": 3575476
        },
        "long": {
            "default": "Christ Church Nichola Town"
        }
    }
]