[
    {
        "ids": {
            "fips": "56",
            "geonames": 864389
        },
        "names": {
            "long": "Alytaus apskritis"
        }
    },
    {
        "ids": {
            "fips": "57",
            "geonames": 864477
        },
        "names": {
            "long": "Kauno apskritis"
        }
    },
    {
        "ids": {
            "fips": "58",
            "geonames": 864478
        },
        "names": {
            "long": "Klaipėdos apskritis"
        }
    },
    {
        "ids": {
            "fips": "59",
            "geonames": 864479
        },
        "names": {
            "long": "Marijampolės apskritis"
        }
    },
    {
        "ids": {
            "fips": "60",
            "geonames": 864480
        },
        "names": {
            "long": "Panevėžys"
        }
    },
    {
        "ids": {
            "fips": "61",
            "geonames": 864481
        },
        "names": {
            "long": "Siauliai"
        }
    },
    {
        "ids": {
            "fips": "62",
            "geonames": 864482
        },
        "names": {
            "long": "Tauragės apskritis"
        }
    },
    {
        "ids": {
            "fips": "63",
            "geonames": 864483
        },
        "names": {
            "long": "Telšių apskritis"
        }
    },
    {
        "ids": {
            "fips": "64",
            "geonames": 864484
        },
        "names": {
            "long": "Utena"
        }
    },
    {
        "ids": {
            "fips": "65",
            "geonames": 864485
        },
        "names": {
            "long": "Vilnius County"
        }
    }
]